<?xml version="1.0" encoding="UTF-8"?>
<objects serializationModel="Studio.02.02.00">
	<object class="AudioFile" id="{ec482512-6f2e-4e7a-9b5f-08b53165468d}">
		<property name="assetPath">
			<value>CaptainCrunchTaunt1.mp3</value>
		</property>
		<property name="frequencyInKHz">
			<value>48</value>
		</property>
		<property name="channelCount">
			<value>2</value>
		</property>
		<property name="length">
			<value>5.2560000000000002</value>
		</property>
		<relationship name="masterAssetFolder">
			<destination>{6a4fa248-7520-4f32-b44f-9670a0e0f620}</destination>
		</relationship>
	</object>
</objects>
